[
    {
        "model": "movies.ott",
        "pk": 1,
        "fields": {
            "logo_path": "/9ghgSC0MA082EL6HLCW3GalykFD.jpg",
            "provider_name": "Apple TV",
            "provider_id": 2
        }
    },
    {
        "model": "movies.ott",
        "pk": 2,
        "fields": {
            "logo_path": "/kwVegvKCinXTPuzZmYT1J3i1HJz.jpg",
            "provider_name": "Netflix Kids",
            "provider_id": 175
        }
    },
    {
        "model": "movies.ott",
        "pk": 3,
        "fields": {
            "logo_path": "/kICQccvOh8AIBMHGkBXJ047xeHN.jpg",
            "provider_name": "Netflix basic with Ads",
            "provider_id": 1796
        }
    },
    {
        "model": "movies.ott",
        "pk": 4,
        "fields": {
            "logo_path": "/2E03IAZsX4ZaUqM7tXlctEPMGWS.jpg",
            "provider_name": "Apple TV Plus",
            "provider_id": 350
        }
    },
    {
        "model": "movies.ott",
        "pk": 5,
        "fields": {
            "logo_path": "/48aHN85OncgXjtl6DOVOJ6Wni4g.jpg",
            "provider_name": "STUDIOCANAL PRESENTS Apple TV Channel",
            "provider_id": 642
        }
    },
    {
        "model": "movies.ott",
        "pk": 6,
        "fields": {
            "logo_path": "/cm1tVzivRWvZjcRSe5dwNqtw26E.jpg",
            "provider_name": "Showtime Apple TV Channel",
            "provider_id": 675
        }
    },
    {
        "model": "movies.ott",
        "pk": 7,
        "fields": {
            "logo_path": "/oTQdXIqM9iewlN4MC2nhKB0gHw.jpg",
            "provider_name": "AMC Plus Apple TV Channel ",
            "provider_id": 1854
        }
    },
    {
        "model": "movies.ott",
        "pk": 8,
        "fields": {
            "logo_path": "/1C5EVCWyQD798CE1DFfcm6oAbxP.jpg",
            "provider_name": "Starz Apple TV Channel",
            "provider_id": 1855
        }
    },
    {
        "model": "movies.ott",
        "pk": 9,
        "fields": {
            "logo_path": "/zu0bo6dHlgBsfd1nk0zz6TBoB3W.jpg",
            "provider_name": "Noggin Apple TV Channel",
            "provider_id": 2032
        }
    },
    {
        "model": "movies.ott",
        "pk": 10,
        "fields": {
            "logo_path": "/a0vfnBfWPAF6OtKZCzlyiW9A9l6.jpg",
            "provider_name": "A&E Crime Central Apple TV Channel",
            "provider_id": 2033
        }
    },
    {
        "model": "movies.ott",
        "pk": 11,
        "fields": {
            "logo_path": "/kx8rGgFYxX6aJkG7RHx2mtijglC.jpg",
            "provider_name": "Acorn TV Apple TV",
            "provider_id": 2034
        }
    },
    {
        "model": "movies.ott",
        "pk": 12,
        "fields": {
            "logo_path": "/voNwdFHk9uc2ZEWKZlwSQDsfRJN.jpg",
            "provider_name": "ALLBLK Apple TV channel",
            "provider_id": 2036
        }
    },
    {
        "model": "movies.ott",
        "pk": 13,
        "fields": {
            "logo_path": "/9jxvmD363A04nuMw9jgyLzeDB3J.jpg",
            "provider_name": "ARD Plus Apple TV channel",
            "provider_id": 2037
        }
    },
    {
        "model": "movies.ott",
        "pk": 14,
        "fields": {
            "logo_path": "/as1NArQkfAnptYQP3VS03GOJPdm.jpg",
            "provider_name": "Arthaus+ Apple TV channel",
            "provider_id": 2038
        }
    },
    {
        "model": "movies.ott",
        "pk": 15,
        "fields": {
            "logo_path": "/yFk3WffvGGUtIjJBSV0pgsciaEB.jpg",
            "provider_name": "BET+  Apple TV channel",
            "provider_id": 2040
        }
    },
    {
        "model": "movies.ott",
        "pk": 16,
        "fields": {
            "logo_path": "/kohVS01u3sP5IkqsSaAKdBit6aP.jpg",
            "provider_name": "BFI Player Apple TV Channel",
            "provider_id": 2041
        }
    },
    {
        "model": "movies.ott",
        "pk": 17,
        "fields": {
            "logo_path": "/eKVmLFHW5PeNhuR7Nedd8OIxW2M.jpg",
            "provider_name": "GuideDoc",
            "provider_id": 100
        }
    },
    {
        "model": "movies.ott",
        "pk": 18,
        "fields": {
            "logo_path": "/oR1aNm1Qu9jQBkW4VrGPWhqbC3P.jpg",
            "provider_name": "Curiosity Stream",
            "provider_id": 190
        }
    },
    {
        "model": "movies.ott",
        "pk": 19,
        "fields": {
            "logo_path": "/dDHyeNrfnloy6skW0j6oIUXFa3Z.jpg",
            "provider_name": "Carnegie Hall+ Apple TV Channel",
            "provider_id": 2042
        }
    },
    {
        "model": "movies.ott",
        "pk": 20,
        "fields": {
            "logo_path": "/1SuB6tXdKaW4qDRDiqm9C1nr1mD.jpg",
            "provider_name": "OUTtv Apple TV Channel",
            "provider_id": 2044
        }
    },
    {
        "model": "movies.ott",
        "pk": 21,
        "fields": {
            "logo_path": "/92iY4soQNVzNM02mHGjqovPdzdF.jpg",
            "provider_name": "UP Faith & Family Apple TV Channel",
            "provider_id": 2045
        }
    },
    {
        "model": "movies.ott",
        "pk": 22,
        "fields": {
            "logo_path": "/kjHUSd4AVuz9duG3xulGJLsYw4E.jpg",
            "provider_name": "Topic Apple TV Channel",
            "provider_id": 2046
        }
    },
    {
        "model": "movies.ott",
        "pk": 23,
        "fields": {
            "logo_path": "/1x0LxXHUibIolT5fxdSamGGMBC3.jpg",
            "provider_name": "Sundance Now Apple TV Channel",
            "provider_id": 2048
        }
    },
    {
        "model": "movies.ott",
        "pk": 24,
        "fields": {
            "logo_path": "/kLfq0I2MwiUFUY9yI1GwOeKxX8f.jpg",
            "provider_name": "Shudder Apple TV Channel",
            "provider_id": 2049
        }
    },
    {
        "model": "movies.ott",
        "pk": 25,
        "fields": {
            "logo_path": "/96HJkA4nMkcOtiqH9oF1YYtGBHK.jpg",
            "provider_name": "ScreenPix Apple TV Channel",
            "provider_id": 2050
        }
    },
    {
        "model": "movies.ott",
        "pk": 26,
        "fields": {
            "logo_path": "/foWKiK4ikpdM72OGN2B8jjyy6OY.jpg",
            "provider_name": "MGM Apple TV Channel",
            "provider_id": 2051
        }
    },
    {
        "model": "movies.ott",
        "pk": 27,
        "fields": {
            "logo_path": "/dy9XKHyf16dSB1Lg7KIrtUwDxIX.jpg",
            "provider_name": "Love Nature Apple TV Channel",
            "provider_id": 2052
        }
    },
    {
        "model": "movies.ott",
        "pk": 28,
        "fields": {
            "logo_path": "/p8i1zUcZYQ7qU6RrGvGbDItvcx4.jpg",
            "provider_name": "Lionsgate Play Apple TV Channel",
            "provider_id": 2053
        }
    },
    {
        "model": "movies.ott",
        "pk": 29,
        "fields": {
            "logo_path": "/hwX55ugBE1qtM62egayb1CHvNEh.jpg",
            "provider_name": "Lifetime Play Apple TV Channel",
            "provider_id": 2054
        }
    },
    {
        "model": "movies.ott",
        "pk": 30,
        "fields": {
            "logo_path": "/cpSQ9P0ntzr1gZcxHIyaryihpgH.jpg",
            "provider_name": "Lifetime Movie Club Apple TV Channel",
            "provider_id": 2055
        }
    },
    {
        "model": "movies.ott",
        "pk": 31,
        "fields": {
            "logo_path": "/tPvmybuDUn84aDps72GiMbvr2xU.jpg",
            "provider_name": "IFC Films Unlimited Apple TV Channel",
            "provider_id": 2056
        }
    },
    {
        "model": "movies.ott",
        "pk": 32,
        "fields": {
            "logo_path": "/fsert5S2L3CWSFyaAODiWPOScmz.jpg",
            "provider_name": "HISTORY Vault Apple TV Channel",
            "provider_id": 2057
        }
    },
    {
        "model": "movies.ott",
        "pk": 33,
        "fields": {
            "logo_path": "/ce9sTSF5WsvqEHv7kxOM1LlQha5.jpg",
            "provider_name": "Hallmark Movies Now Apple TV Channel",
            "provider_id": 2058
        }
    },
    {
        "model": "movies.ott",
        "pk": 34,
        "fields": {
            "logo_path": "/cqgeSQHqKEkfcmsiy7GoCnf1Q2I.jpg",
            "provider_name": "Eros Now Select Apple TV Channel",
            "provider_id": 2059
        }
    },
    {
        "model": "movies.ott",
        "pk": 35,
        "fields": {
            "logo_path": "/z9x1xFFKjHTYlLYWtiPhAjN4jOp.jpg",
            "provider_name": "CuriosityStream Apple TV Channel",
            "provider_id": 2060
        }
    },
    {
        "model": "movies.ott",
        "pk": 36,
        "fields": {
            "logo_path": "/zXCdY4pczONheFCU9GkrMbGI1o5.jpg",
            "provider_name": "Cinemax Apple TV Channel",
            "provider_id": 2061
        }
    },
    {
        "model": "movies.ott",
        "pk": 37,
        "fields": {
            "logo_path": "/xp12VXTZfunk568CAPs2Xqknimq.jpg",
            "provider_name": "Britbox Apple TV Channel ",
            "provider_id": 1852
        }
    },
    {
        "model": "movies.ott",
        "pk": 38,
        "fields": {
            "logo_path": "/tJqmTmQ8jp9WfyaZfApHK8lSywA.jpg",
            "provider_name": "Paramount Plus Apple TV Channel ",
            "provider_id": 1853
        }
    },
    {
        "model": "movies.ott",
        "pk": 39,
        "fields": {
            "logo_path": "/pbpMk2JmcoNnQwx5JGpXngfoWtp.jpg",
            "provider_name": "Netflix",
            "provider_id": 8
        }
    },
    {
        "model": "movies.ott",
        "pk": 40,
        "fields": {
            "logo_path": "/dQeAar5H991VYporEjUspolDarG.jpg",
            "provider_name": "Amazon Prime Video",
            "provider_id": 9
        }
    },
    {
        "model": "movies.ott",
        "pk": 41,
        "fields": {
            "logo_path": "/dQeAar5H991VYporEjUspolDarG.jpg",
            "provider_name": "Amazon Prime Video",
            "provider_id": 119
        }
    },
    {
        "model": "movies.ott",
        "pk": 42,
        "fields": {
            "logo_path": "/dQeAar5H991VYporEjUspolDarG.jpg",
            "provider_name": "Amazon Prime Video with Ads",
            "provider_id": 2100
        }
    },
    {
        "model": "movies.ott",
        "pk": 43,
        "fields": {
            "logo_path": "/ctse3rS9jiPiOvDwBEFtpVUOnnq.jpg",
            "provider_name": "Adrenalina Pura Apple TV channel",
            "provider_id": 2107
        }
    },
    {
        "model": "movies.ott",
        "pk": 44,
        "fields": {
            "logo_path": "/seGSXajazLMCKGB5hnRCidtjay1.jpg",
            "provider_name": "Amazon Video",
            "provider_id": 10
        }
    },
    {
        "model": "movies.ott",
        "pk": 45,
        "fields": {
            "logo_path": "/esiLBRzDUwodjfN8gA4qj7l3ZF7.jpg",
            "provider_name": "Starz Play Amazon Channel",
            "provider_id": 194
        }
    },
    {
        "model": "movies.ott",
        "pk": 46,
        "fields": {
            "logo_path": "/1wYmvbAuVZz2JnKvYfYN8Qolnb.jpg",
            "provider_name": "AcornTV Amazon Channel",
            "provider_id": 196
        }
    },
    {
        "model": "movies.ott",
        "pk": 47,
        "fields": {
            "logo_path": "/tLBLABfFYYETf9Zk8gKEWnjhMai.jpg",
            "provider_name": "BritBox Amazon Channel",
            "provider_id": 197
        }
    },
    {
        "model": "movies.ott",
        "pk": 48,
        "fields": {
            "logo_path": "/3eVIcUeRXji5SBV7gEv4f5U4CqV.jpg",
            "provider_name": "Fandor Amazon Channel",
            "provider_id": 199
        }
    },
    {
        "model": "movies.ott",
        "pk": 49,
        "fields": {
            "logo_path": "/a4IDLKjvP5gvq7tNlg2Xw5YyEkI.jpg",
            "provider_name": "MUBI Amazon Channel",
            "provider_id": 201
        }
    },
    {
        "model": "movies.ott",
        "pk": 50,
        "fields": {
            "logo_path": "/vmXC3D9Kqtt9TEohDEmcaxnLYA5.jpg",
            "provider_name": "Screambox Amazon Channel",
            "provider_id": 202
        }
    },
    {
        "model": "movies.ott",
        "pk": 51,
        "fields": {
            "logo_path": "/palbLJjkRhNAccU32ycThJNcbI5.jpg",
            "provider_name": "Showtime Amazon Channel",
            "provider_id": 203
        }
    },
    {
        "model": "movies.ott",
        "pk": 52,
        "fields": {
            "logo_path": "/qb6Lj5BhNJavdmRVDzAqAjd4Tj3.jpg",
            "provider_name": "Shudder Amazon Channel",
            "provider_id": 204
        }
    },
    {
        "model": "movies.ott",
        "pk": 53,
        "fields": {
            "logo_path": "/i8PzzzOVJfXWLE1v5Up7nGTWWhp.jpg",
            "provider_name": "Sundance Now Amazon Channel",
            "provider_id": 205
        }
    },
    {
        "model": "movies.ott",
        "pk": 54,
        "fields": {
            "logo_path": "/jhhFTFVWjKVi2JjDYoqoI4dHsmL.jpg",
            "provider_name": "BBC Player Amazon Channel",
            "provider_id": 285
        }
    },
    {
        "model": "movies.ott",
        "pk": 55,
        "fields": {
            "logo_path": "/FtIkEXYkqTxKwCwLK79yKJW8i7.jpg",
            "provider_name": "ZDF Herzkino Amazon Channel",
            "provider_id": 286
        }
    },
    {
        "model": "movies.ott",
        "pk": 56,
        "fields": {
            "logo_path": "/4SJW6thrCvN6ya2hO6naksfRZDF.jpg",
            "provider_name": "BFI Player Amazon Channel",
            "provider_id": 287
        }
    },
    {
        "model": "movies.ott",
        "pk": 57,
        "fields": {
            "logo_path": "/3CPBjF6tQQONCEvqC6KIIkiUG81.jpg",
            "provider_name": "Boomerang Amazon Channel",
            "provider_id": 288
        }
    },
    {
        "model": "movies.ott",
        "pk": 58,
        "fields": {
            "logo_path": "/ohcwolMl8E743CkS8MnhmJKOlRj.jpg",
            "provider_name": "Cinemax Amazon Channel",
            "provider_id": 289
        }
    },
    {
        "model": "movies.ott",
        "pk": 59,
        "fields": {
            "logo_path": "/614YTzAiVrSIm7bIVcwg4lIMQr7.jpg",
            "provider_name": "Hallmark Movies Now Amazon Channel",
            "provider_id": 290
        }
    },
    {
        "model": "movies.ott",
        "pk": 60,
        "fields": {
            "logo_path": "/hTAIgvUnmu1Yv0wFVJRu9KKAPtJ.jpg",
            "provider_name": "MZ Choice Amazon Channel",
            "provider_id": 291
        }
    },
    {
        "model": "movies.ott",
        "pk": 61,
        "fields": {
            "logo_path": "/lIXDKV7LrZfF3SR2m8EQrMVRI5C.jpg",
            "provider_name": "PBS Kids Amazon Channel",
            "provider_id": 293
        }
    },
    {
        "model": "movies.ott",
        "pk": 62,
        "fields": {
            "logo_path": "/xN1vKpcypShJrWmf1t3dyGJM7sO.jpg",
            "provider_name": "PBS Masterpiece Amazon Channel",
            "provider_id": 294
        }
    },
    {
        "model": "movies.ott",
        "pk": 63,
        "fields": {
            "logo_path": "/769jLV69ZSa0x4sy9BZZQbizvuk.jpg",
            "provider_name": "Viewster Amazon Channel",
            "provider_id": 295
        }
    },
    {
        "model": "movies.ott",
        "pk": 64,
        "fields": {
            "logo_path": "/ni0t0Bj4HRAQ9f6zSv1Bl9MDjLK.jpg",
            "provider_name": "Filmtastic Amazon Channel",
            "provider_id": 334
        }
    },
    {
        "model": "movies.ott",
        "pk": 65,
        "fields": {
            "logo_path": "/97yvRBw1GzX7fXprcF80er19ot.jpg",
            "provider_name": "Disney Plus",
            "provider_id": 337
        }
    },
    {
        "model": "movies.ott",
        "pk": 66,
        "fields": {
            "logo_path": "/2AvUqoIHAq2lLxRy2IxOBUgCYef.jpg",
            "provider_name": "Bet+ Amazon Channel",
            "provider_id": 343
        }
    },
    {
        "model": "movies.ott",
        "pk": 67,
        "fields": {
            "logo_path": "/2ino0WmHA4GROB7NYKzT6PGqLcb.jpg",
            "provider_name": "AMC+ Amazon Channel",
            "provider_id": 528
        }
    },
    {
        "model": "movies.ott",
        "pk": 68,
        "fields": {
            "logo_path": "/9MABvFilVMUAV86vLUgBgeM5LQQ.jpg",
            "provider_name": "Amazon Arthaus Channel",
            "provider_id": 533
        }
    },
    {
        "model": "movies.ott",
        "pk": 69,
        "fields": {
            "logo_path": "/hExO4PtimLIYn3kBOrzsejNv7cT.jpg",
            "provider_name": "Paramount+ Amazon Channel",
            "provider_id": 582
        }
    },
    {
        "model": "movies.ott",
        "pk": 70,
        "fields": {
            "logo_path": "/efu1Cqc63XrPBoreYnf2mn0Nizj.jpg",
            "provider_name": "MGM Plus Amazon Channel",
            "provider_id": 583
        }
    },
    {
        "model": "movies.ott",
        "pk": 71,
        "fields": {
            "logo_path": "/lgudHqEtTOzkMWlpTjU1oUyoUSZ.jpg",
            "provider_name": "Discovery+ Amazon Channel",
            "provider_id": 584
        }
    },
    {
        "model": "movies.ott",
        "pk": 72,
        "fields": {
            "logo_path": "/tw81Wj2gaVL30O7CvzfsqTLMxQg.jpg",
            "provider_name": "IFC Amazon Channel",
            "provider_id": 587
        }
    },
    {
        "model": "movies.ott",
        "pk": 73,
        "fields": {
            "logo_path": "/efu1Cqc63XrPBoreYnf2mn0Nizj.jpg",
            "provider_name": "MGM Amazon Channel",
            "provider_id": 588
        }
    },
    {
        "model": "movies.ott",
        "pk": 74,
        "fields": {
            "logo_path": "/4KZlGfHQEza2dBf3HVk4oWmh611.jpg",
            "provider_name": "TELETOON+ Amazon Channel",
            "provider_id": 589
        }
    },
    {
        "model": "movies.ott",
        "pk": 75,
        "fields": {
            "logo_path": "/6xQrNQoTmXWhaJj4O8u2FRsXBXs.jpg",
            "provider_name": "Eros Now Amazon Channel",
            "provider_id": 595
        }
    },
    {
        "model": "movies.ott",
        "pk": 76,
        "fields": {
            "logo_path": "/u4OSH6NN7bdHRJJVLwozPa0jDUj.jpg",
            "provider_name": "Arrow Video Amazon Channel",
            "provider_id": 596
        }
    },
    {
        "model": "movies.ott",
        "pk": 77,
        "fields": {
            "logo_path": "/xIu1EW7y2EC7RD3Wqe0Ogi5NAuo.jpg",
            "provider_name": "Full Moon Amazon Channel",
            "provider_id": 597
        }
    },
    {
        "model": "movies.ott",
        "pk": 78,
        "fields": {
            "logo_path": "/l4h4b2esfTb7evLRiLrMjk6rsHj.jpg",
            "provider_name": "Pokémon Amazon Channel",
            "provider_id": 599
        }
    },
    {
        "model": "movies.ott",
        "pk": 79,
        "fields": {
            "logo_path": "/ivRp15loTWoVy3eEHALoYEyXI8J.jpg",
            "provider_name": "Shout! Factory Amazon Channel",
            "provider_id": 600
        }
    },
    {
        "model": "movies.ott",
        "pk": 80,
        "fields": {
            "logo_path": "/xJ3B83btVmp4wyRGRRRgWCibTLI.jpg",
            "provider_name": "FilmBox Live Amazon Channel",
            "provider_id": 602
        }
    },
    {
        "model": "movies.ott",
        "pk": 81,
        "fields": {
            "logo_path": "/tLbUhvK1RcA5I4JHndxf5dprkE7.jpg",
            "provider_name": "CuriosityStream Amazon Channel",
            "provider_id": 603
        }
    },
    {
        "model": "movies.ott",
        "pk": 82,
        "fields": {
            "logo_path": "/91oRDZySWtw60ei006uQ45gmjXD.jpg",
            "provider_name": "DocuBay Amazon Channel",
            "provider_id": 604
        }
    },
    {
        "model": "movies.ott",
        "pk": 83,
        "fields": {
            "logo_path": "/5W6vTKE684EhdITeMUjdcTIBGdh.jpg",
            "provider_name": "Super Channel Amazon Channel",
            "provider_id": 605
        }
    },
    {
        "model": "movies.ott",
        "pk": 84,
        "fields": {
            "logo_path": "/djTJ7pAkIhmPaN3eTA6wTUrphNG.jpg",
            "provider_name": "StackTV Amazon Channel",
            "provider_id": 606
        }
    },
    {
        "model": "movies.ott",
        "pk": 85,
        "fields": {
            "logo_path": "/d0KmcInHpiF44ahOLrXCQATEFmD.jpg",
            "provider_name": "OUTtv Amazon Channel",
            "provider_id": 607
        }
    },
    {
        "model": "movies.ott",
        "pk": 86,
        "fields": {
            "logo_path": "/bSy9zFiZtbKBHIyOu0H2Fs5cJmx.jpg",
            "provider_name": "Love Nature Amazon Channel",
            "provider_id": 608
        }
    },
    {
        "model": "movies.ott",
        "pk": 87,
        "fields": {
            "logo_path": "/bEgGGEDgBczZcZRJ6x1MtTym2LV.jpg",
            "provider_name": "Smithsonian Channel Amazon Channel",
            "provider_id": 609
        }
    },
    {
        "model": "movies.ott",
        "pk": 88,
        "fields": {
            "logo_path": "/2WEzLLWbvMLHSNkAjYrIeDOmLJM.jpg",
            "provider_name": "BBC Earth Amazon Channel",
            "provider_id": 610
        }
    },
    {
        "model": "movies.ott",
        "pk": 89,
        "fields": {
            "logo_path": "/r9JMtkJn6eE0i8Vi9ONLVci7Hnv.jpg",
            "provider_name": "UMC Amazon Channel",
            "provider_id": 612
        }
    },
    {
        "model": "movies.ott",
        "pk": 90,
        "fields": {
            "logo_path": "/iM7Ed1d7mYT3DQWSqLoW3tIN4uS.jpg",
            "provider_name": "Filmlegenden Amazon Channel",
            "provider_id": 678
        }
    },
    {
        "model": "movies.ott",
        "pk": 91,
        "fields": {
            "logo_path": "/coWnECpOyKLWMTSlXkfT2PhLs9E.jpg",
            "provider_name": "Cinema of Hearts Amazon Channel",
            "provider_id": 679
        }
    },
    {
        "model": "movies.ott",
        "pk": 92,
        "fields": {
            "logo_path": "/jG5tKt6JoHsYRoUq6Wg8i9QuHt2.jpg",
            "provider_name": "Bloody Movies Amazon Channel",
            "provider_id": 680
        }
    },
    {
        "model": "movies.ott",
        "pk": 93,
        "fields": {
            "logo_path": "/3fhcb4cThixkfNpOudnpLcosTCA.jpg",
            "provider_name": "Film Total Amazon Channel",
            "provider_id": 681
        }
    },
    {
        "model": "movies.ott",
        "pk": 94,
        "fields": {
            "logo_path": "/xht0G3uRLcTgjxRz3cDHuf8KKUw.jpg",
            "provider_name": "Looke Amazon Channel",
            "provider_id": 683
        }
    },
    {
        "model": "movies.ott",
        "pk": 95,
        "fields": {
            "logo_path": "/2GQVxfaiWA4n93I7sJDJf1b6NqS.jpg",
            "provider_name": "FlixOlé Amazon Channel",
            "provider_id": 684
        }
    },
    {
        "model": "movies.ott",
        "pk": 96,
        "fields": {
            "logo_path": "/oYsPBkqP7QjliFT758DrR9i2mpl.jpg",
            "provider_name": "OCS Amazon Channel ",
            "provider_id": 685
        }
    },
    {
        "model": "movies.ott",
        "pk": 97,
        "fields": {
            "logo_path": "/7Zy6GqC8lQEvfBlWC1bJcaJzPRd.jpg",
            "provider_name": "Home of Horror Amazon Channel",
            "provider_id": 686
        }
    },
    {
        "model": "movies.ott",
        "pk": 98,
        "fields": {
            "logo_path": "/tnQ5PGryncrVxE9bK6nxif82wtd.jpg",
            "provider_name": "Arthouse CNMA Amazon Channel",
            "provider_id": 687
        }
    },
    {
        "model": "movies.ott",
        "pk": 99,
        "fields": {
            "logo_path": "/2nFBw1zMzN1AujFaCsmsgSKWdfS.jpg",
            "provider_name": "ShortsTV Amazon Channel",
            "provider_id": 688
        }
    },
    {
        "model": "movies.ott",
        "pk": 100,
        "fields": {
            "logo_path": "/32R4lsqOPclNhb3qV613J8T8mdL.jpg",
            "provider_name": "TVCortos Amazon Channel",
            "provider_id": 689
        }
    },
    {
        "model": "movies.ott",
        "pk": 101,
        "fields": {
            "logo_path": "/t7I2Tx6Q7Nz96KexIPjkzUJOCbt.jpg",
            "provider_name": "Pongalo Amazon Channel  ",
            "provider_id": 690
        }
    },
    {
        "model": "movies.ott",
        "pk": 102,
        "fields": {
            "logo_path": "/9aLd9gAK6xHtWK2tXDYq1fOqzJA.jpg",
            "provider_name": "Turk On Video Amazon Channel",
            "provider_id": 693
        }
    },
    {
        "model": "movies.ott",
        "pk": 103,
        "fields": {
            "logo_path": "/29VK28jsSjFWHdXl1lxPb2SGmAk.jpg",
            "provider_name": "Hollywood Suite Amazon Channel",
            "provider_id": 705
        }
    },
    {
        "model": "movies.ott",
        "pk": 104,
        "fields": {
            "logo_path": "/9NYihXY9biyXFJSZQq5HIGu1n8B.jpg",
            "provider_name": "Moviedome Plus Amazon Channel",
            "provider_id": 706
        }
    },
    {
        "model": "movies.ott",
        "pk": 105,
        "fields": {
            "logo_path": "/a2wCZ9ultzAbjAaG6JMiCFJoy9s.jpg",
            "provider_name": "Aniverse Amazon Channel",
            "provider_id": 707
        }
    },
    {
        "model": "movies.ott",
        "pk": 106,
        "fields": {
            "logo_path": "/9T5H28SXBkzmnZYy2iRfI7GzwLL.jpg",
            "provider_name": "Superfresh Amazon Channel",
            "provider_id": 708
        }
    },
    {
        "model": "movies.ott",
        "pk": 107,
        "fields": {
            "logo_path": "/eMoqH13BYzIC1wDlhONhHfDM3DN.jpg",
            "provider_name": "Comedy Central Plus Amazon Channel",
            "provider_id": 1706
        }
    },
    {
        "model": "movies.ott",
        "pk": 108,
        "fields": {
            "logo_path": "/AvUM6aAqYh7JxUokb5T5ERn3KMs.jpg",
            "provider_name": "BluTV Amazon Channel",
            "provider_id": 1707
        }
    },
    {
        "model": "movies.ott",
        "pk": 109,
        "fields": {
            "logo_path": "/cYzZyot2IuGUYUXLvw6BMBT6v9p.jpg",
            "provider_name": "GRJNGO Amazon Channel",
            "provider_id": 1709
        }
    },
    {
        "model": "movies.ott",
        "pk": 110,
        "fields": {
            "logo_path": "/g06QZd5k4bjDEcZ3J97jb3rNlfB.jpg",
            "provider_name": "MTV Plus Amazon Channel",
            "provider_id": 1711
        }
    },
    {
        "model": "movies.ott",
        "pk": 111,
        "fields": {
            "logo_path": "/gHBdFYhxdeLHl8jimTDwA1bFv01.jpg",
            "provider_name": "RTL Passion Amazon Channel",
            "provider_id": 1712
        }
    },
    {
        "model": "movies.ott",
        "pk": 112,
        "fields": {
            "logo_path": "/xXN970tHrMfL7BQUTVSu96IY9gs.jpg",
            "provider_name": "Silverline Amazon Channel",
            "provider_id": 1713
        }
    },
    {
        "model": "movies.ott",
        "pk": 113,
        "fields": {
            "logo_path": "/7gkA2RRoHTdGf8KXBKkMbevqN1p.jpg",
            "provider_name": "Sony AXN Amazon Channel",
            "provider_id": 1714
        }
    },
    {
        "model": "movies.ott",
        "pk": 114,
        "fields": {
            "logo_path": "/q77DpszIupURiKGDeFdSHo7TsTF.jpg",
            "provider_name": "Infinity Selection Amazon Channel",
            "provider_id": 1726
        }
    },
    {
        "model": "movies.ott",
        "pk": 115,
        "fields": {
            "logo_path": "/9bRB5nKmQPZYGQkUtLRhw1w0IcD.jpg",
            "provider_name": "CG Collection Amazon channel",
            "provider_id": 1727
        }
    },
    {
        "model": "movies.ott",
        "pk": 116,
        "fields": {
            "logo_path": "/iZzlUo191ynXNpPNdcY8vvlYSf6.jpg",
            "provider_name": "iWonder Full Amazon channel",
            "provider_id": 1728
        }
    },
    {
        "model": "movies.ott",
        "pk": 117,
        "fields": {
            "logo_path": "/xdUXTl4ontqdKv9ZpSBZKiOTyWm.jpg",
            "provider_name": "Full Action Amazon Channel",
            "provider_id": 1729
        }
    },
    {
        "model": "movies.ott",
        "pk": 118,
        "fields": {
            "logo_path": "/gQoeIu88CiTF54vYRGwTONHEAtO.jpg",
            "provider_name": "Cine Comico Amazon Channel",
            "provider_id": 1730
        }
    },
    {
        "model": "movies.ott",
        "pk": 119,
        "fields": {
            "logo_path": "/uPhMKOrup9jtJHIci8FXo3D6y5x.jpg",
            "provider_name": "Universcine Amazon Channel",
            "provider_id": 1732
        }
    },
    {
        "model": "movies.ott",
        "pk": 120,
        "fields": {
            "logo_path": "/1PhTUiq01Z82nvuJlDNYtBnRRN0.jpg",
            "provider_name": "Action Max Amazon Channel",
            "provider_id": 1733
        }
    },
    {
        "model": "movies.ott",
        "pk": 121,
        "fields": {
            "logo_path": "/4clLD3X9nTapdRey1FgcSUPYRy3.jpg",
            "provider_name": "Filmo Amazon Channel",
            "provider_id": 1734
        }
    },
    {
        "model": "movies.ott",
        "pk": 122,
        "fields": {
            "logo_path": "/nJ43DUei5yK9wWG3g9YpYT4UfN4.jpg",
            "provider_name": "Insomnia Amazon Channel",
            "provider_id": 1735
        }
    },
    {
        "model": "movies.ott",
        "pk": 123,
        "fields": {
            "logo_path": "/vBbNBDZnpnhgHe5ZO9CVur4DmkG.jpg",
            "provider_name": "Shadowz Amazon Channel",
            "provider_id": 1736
        }
    },
    {
        "model": "movies.ott",
        "pk": 124,
        "fields": {
            "logo_path": "/zg1uFDzIchkwrwOW6dq7LFxB4n6.jpg",
            "provider_name": "INA  madelen Amazon Channel",
            "provider_id": 1737
        }
    },
    {
        "model": "movies.ott",
        "pk": 125,
        "fields": {
            "logo_path": "/yXSOt0AKxG28wXhnBaogQGwF7Rq.jpg",
            "provider_name": "Benshi Amazon Channel",
            "provider_id": 1738
        }
    },
    {
        "model": "movies.ott",
        "pk": 126,
        "fields": {
            "logo_path": "/yISpVXhf6axqiHh6lBvJ8RRrZ8v.jpg",
            "provider_name": "Planet Horror Amazon Channel",
            "provider_id": 1740
        }
    },
    {
        "model": "movies.ott",
        "pk": 127,
        "fields": {
            "logo_path": "/tM1HabyA45cnckBEhLS7hAVga5g.jpg",
            "provider_name": "Dizi Amazon Channel",
            "provider_id": 1741
        }
    },
    {
        "model": "movies.ott",
        "pk": 128,
        "fields": {
            "logo_path": "/tGvAD4O9obFP3DfOrDn8NaRQ6eT.jpg",
            "provider_name": "Acontra Plus Amazon Channel",
            "provider_id": 1742
        }
    },
    {
        "model": "movies.ott",
        "pk": 129,
        "fields": {
            "logo_path": "/aJECXkHekrkuRZ7ABF5YR9DVDd8.jpg",
            "provider_name": "Historia y Actualidad Amazon Channel",
            "provider_id": 1743
        }
    },
    {
        "model": "movies.ott",
        "pk": 130,
        "fields": {
            "logo_path": "/jTtwvCgQxD8W7vljH5pH28PfYQD.jpg",
            "provider_name": "Icon Film Amazon Channel",
            "provider_id": 1744
        }
    },
    {
        "model": "movies.ott",
        "pk": 131,
        "fields": {
            "logo_path": "/kSONYxM7a0mESEjCaqaozVTdByB.jpg",
            "provider_name": "Curzon Amazon Channel",
            "provider_id": 1745
        }
    },
    {
        "model": "movies.ott",
        "pk": 132,
        "fields": {
            "logo_path": "/x2cjJAyU8CLwyYHaIxzzEjXJFU8.jpg",
            "provider_name": "Hallmark TV Amazon Channel",
            "provider_id": 1746
        }
    },
    {
        "model": "movies.ott",
        "pk": 133,
        "fields": {
            "logo_path": "/mLif0L2p0M2AK4pbqHOBqLwB3bP.jpg",
            "provider_name": "Studiocanal Presents Amazon Channel",
            "provider_id": 1747
        }
    },
    {
        "model": "movies.ott",
        "pk": 134,
        "fields": {
            "logo_path": "/6WQqJyaFd0fmLLE6WIjFQyEyAFj.jpg",
            "provider_name": "Sooner Amazon Channel",
            "provider_id": 1757
        }
    },
    {
        "model": "movies.ott",
        "pk": 135,
        "fields": {
            "logo_path": "/rYszOzWFzq7xPffwJ7XN5rJRI7u.jpg",
            "provider_name": "Love and Passion Amazon Channel",
            "provider_id": 1788
        }
    },
    {
        "model": "movies.ott",
        "pk": 136,
        "fields": {
            "logo_path": "/esiLBRzDUwodjfN8gA4qj7l3ZF7.jpg",
            "provider_name": "Starz Amazon Channel",
            "provider_id": 1794
        }
    },
    {
        "model": "movies.ott",
        "pk": 137,
        "fields": {
            "logo_path": "/3VYyCBiG2WTCZ2tGzTkWvoXTeqi.jpg",
            "provider_name": "Studiocanal Presents MOVIECULT Amazon Channel",
            "provider_id": 1805
        }
    },
    {
        "model": "movies.ott",
        "pk": 138,
        "fields": {
            "logo_path": "/tHX1KI8VdAzKWMxSgPKqKfHcxFA.jpg",
            "provider_name": "Studiocanal Presents ALLSTARS Amazon Channel",
            "provider_id": 1806
        }
    },
    {
        "model": "movies.ott",
        "pk": 139,
        "fields": {
            "logo_path": "/QAtDmj6XHlkPvw5xAjF08ZQARh.jpg",
            "provider_name": "Cohen Media Amazon Channel",
            "provider_id": 1811
        }
    },
    {
        "model": "movies.ott",
        "pk": 140,
        "fields": {
            "logo_path": "/erfmV26akboHUerxGjpl8pBwww3.jpg",
            "provider_name": "Max Amazon Channel",
            "provider_id": 1825
        }
    },
    {
        "model": "movies.ott",
        "pk": 141,
        "fields": {
            "logo_path": "/6XLxMoxqVCZRTkAavMwnsbpx3XU.jpg",
            "provider_name": "Pass Warner Amazon Channel",
            "provider_id": 1870
        }
    },
    {
        "model": "movies.ott",
        "pk": 142,
        "fields": {
            "logo_path": "/2HsZxiwKi9Ym91r6WY9ojORvq79.jpg",
            "provider_name": "BrutX Amazon Channel",
            "provider_id": 1887
        }
    },
    {
        "model": "movies.ott",
        "pk": 143,
        "fields": {
            "logo_path": "/9jmtFeqCWvTSYpMMUPNhk8JNJWS.jpg",
            "provider_name": "Animation Digital Network Amazon Channel",
            "provider_id": 1888
        }
    },
    {
        "model": "movies.ott",
        "pk": 144,
        "fields": {
            "logo_path": "/4ABGBjAMtRrYUrr0w3QfanuiaoB.jpg",
            "provider_name": "Universal+ Amazon Channel",
            "provider_id": 1889
        }
    },
    {
        "model": "movies.ott",
        "pk": 145,
        "fields": {
            "logo_path": "/s7ZjSKXOtjKBb7hAzBm3b0iY0SG.jpg",
            "provider_name": "alleskino Amazon Channel",
            "provider_id": 1891
        }
    },
    {
        "model": "movies.ott",
        "pk": 146,
        "fields": {
            "logo_path": "/5Qe65kN95Z0CytOaG3I8bytdW7A.jpg",
            "provider_name": "RTL Crime Amazon Channel",
            "provider_id": 1892
        }
    },
    {
        "model": "movies.ott",
        "pk": 147,
        "fields": {
            "logo_path": "/vM8Oe43bljZqRenO2xSIRHT7GMN.jpg",
            "provider_name": "CineAutore Amazon Channel",
            "provider_id": 1894
        }
    },
    {
        "model": "movies.ott",
        "pk": 148,
        "fields": {
            "logo_path": "/xcXI50PQIBsRDAP6eEpv09Vz8SG.jpg",
            "provider_name": "Anime Generation Amazon Channel",
            "provider_id": 1895
        }
    },
    {
        "model": "movies.ott",
        "pk": 149,
        "fields": {
            "logo_path": "/vXXpcM5yoD8GBWi6U50dOiKgukH.jpg",
            "provider_name": "Raro Video Amazon Channel",
            "provider_id": 1896
        }
    },
    {
        "model": "movies.ott",
        "pk": 150,
        "fields": {
            "logo_path": "/sL8ViH6zWOe07xHoiwxUwCXy890.jpg",
            "provider_name": "MIDNIGHT FACTORY Amazon Channel",
            "provider_id": 1897
        }
    },
    {
        "model": "movies.ott",
        "pk": 151,
        "fields": {
            "logo_path": "/oRfWFOG7XbNO1ZSICEnRzmUt7bT.jpg",
            "provider_name": "Amazon miniTV",
            "provider_id": 1898
        }
    },
    {
        "model": "movies.ott",
        "pk": 152,
        "fields": {
            "logo_path": "/j7wdfXtHKUpV9CNwnXUa68HImFx.jpg",
            "provider_name": "Crunchyroll Amazon Channel",
            "provider_id": 1968
        }
    },
    {
        "model": "movies.ott",
        "pk": 153,
        "fields": {
            "logo_path": "/mmDWKHiDLmHDo2OWnduQuI1T4bh.jpg",
            "provider_name": "ZDF Select Amazon Channel ",
            "provider_id": 1989
        }
    },
    {
        "model": "movies.ott",
        "pk": 154,
        "fields": {
            "logo_path": "/xT5I4zZ2XTLhOVA5ooQIsqjSC3R.jpg",
            "provider_name": "Carnegie Hall+ Amazon Channel",
            "provider_id": 2071
        }
    },
    {
        "model": "movies.ott",
        "pk": 155,
        "fields": {
            "logo_path": "/fr8lHD0EAYU01UIhg6u8kJrk7jQ.jpg",
            "provider_name": "HISTORY Vault Amazon Channel",
            "provider_id": 2073
        }
    },
    {
        "model": "movies.ott",
        "pk": 156,
        "fields": {
            "logo_path": "/yVbjPWEbsStanRAxwKMDARVOvsn.jpg",
            "provider_name": "Lionsgate Play Amazon Channel",
            "provider_id": 2074
        }
    },
    {
        "model": "movies.ott",
        "pk": 157,
        "fields": {
            "logo_path": "/zNYEUs0Z5t7jJqnLTtla8v6AoS4.jpg",
            "provider_name": "Lifetime Play Amazon Channel",
            "provider_id": 2075
        }
    },
    {
        "model": "movies.ott",
        "pk": 158,
        "fields": {
            "logo_path": "/bKWKqZYT3wrpq1Lyi2qSmx1qlqh.jpg",
            "provider_name": "Lifetime Movie Club Amazon Channel",
            "provider_id": 2089
        }
    },
    {
        "model": "movies.ott",
        "pk": 159,
        "fields": {
            "logo_path": "/5lcKyzjIFl9ur2Nk8YsXd5kR7vc.jpg",
            "provider_name": "Adrenalina Pura Amazon channel",
            "provider_id": 2106
        }
    },
    {
        "model": "movies.ott",
        "pk": 160,
        "fields": {
            "logo_path": "/5kpTR2iwaoBk9AkPZvlfgeYvbsv.jpg",
            "provider_name": "Far East Amazon Channel ",
            "provider_id": 2108
        }
    },
    {
        "model": "movies.ott",
        "pk": 161,
        "fields": {
            "logo_path": "/d8HzRaIa5aGE5mJB1SsIA9hODdx.jpg",
            "provider_name": "DisneyNOW",
            "provider_id": 508
        }
    },
    {
        "model": "movies.ott",
        "pk": 162,
        "fields": {
            "logo_path": "/hPcjSaWfMwEqXaCMu7Fkb529Dkc.jpg",
            "provider_name": "wavve",
            "provider_id": 356
        }
    },
    {
        "model": "movies.ott",
        "pk": 163,
        "fields": {
            "logo_path": "/5gmEivxOGPdq4Afpq1f8ktLtEW1.jpg",
            "provider_name": "Watcha",
            "provider_id": 97
        }
    },
    {
        "model": "movies.ott",
        "pk": 164,
        "fields": {
            "logo_path": "/crFbxg6jkiKc14gpIGMkre9Y3mu.jpg",
            "provider_name": "Naver Store",
            "provider_id": 96
        }
    },
    {
        "model": "movies.ott",
        "pk": 165,
        "fields": {
            "logo_path": "/8z7rC8uIDaTM91X0ZfkRf04ydj2.jpg",
            "provider_name": "Google Play Movies",
            "provider_id": 3
        }
    },
    {
        "model": "movies.ott",
        "pk": 166,
        "fields": {
            "logo_path": "/fj9Y8iIMFUC6952HwxbGixTQPb7.jpg",
            "provider_name": "MUBI",
            "provider_id": 11
        }
    },
    {
        "model": "movies.ott",
        "pk": 167,
        "fields": {
            "logo_path": "/k2YgZyxij5RcnS1qqUYEUrJB4oQ.jpg",
            "provider_name": "Spamflix",
            "provider_id": 521
        }
    },
    {
        "model": "movies.ott",
        "pk": 168,
        "fields": {
            "logo_path": "/5zqbck5mo8PuVbGu2ngBUdn5Yga.jpg",
            "provider_name": "DOCSVILLE",
            "provider_id": 475
        }
    },
    {
        "model": "movies.ott",
        "pk": 169,
        "fields": {
            "logo_path": "/vLZKlXUNDcZR7ilvfY9Wr9k80FZ.jpg",
            "provider_name": "Plex",
            "provider_id": 538
        }
    },
    {
        "model": "movies.ott",
        "pk": 170,
        "fields": {
            "logo_path": "/6dET59jNU0ADysghEjl8Unuc7Ca.jpg",
            "provider_name": "WOW Presents Plus",
            "provider_id": 546
        }
    },
    {
        "model": "movies.ott",
        "pk": 171,
        "fields": {
            "logo_path": "/9r5zFWuYnwjzO1JrNjSbLQwUc3P.jpg",
            "provider_name": "WOW",
            "provider_id": 30
        }
    },
    {
        "model": "movies.ott",
        "pk": 172,
        "fields": {
            "logo_path": "/mSH24WQcRDJ2fsL5iucXqqRnSRb.jpg",
            "provider_name": "Magellan TV",
            "provider_id": 551
        }
    },
    {
        "model": "movies.ott",
        "pk": 173,
        "fields": {
            "logo_path": "/6IYZ4NjwPikxN7J9cfSmuyeHeMm.jpg",
            "provider_name": "BroadwayHD",
            "provider_id": 554
        }
    },
    {
        "model": "movies.ott",
        "pk": 174,
        "fields": {
            "logo_path": "/eUBxtrqO26wAJfYOZJOzhQEo3mm.jpg",
            "provider_name": "Filmzie",
            "provider_id": 559
        }
    },
    {
        "model": "movies.ott",
        "pk": 175,
        "fields": {
            "logo_path": "/x6nRFzF32hCzMHaVM4RHRo7lsgS.jpg",
            "provider_name": "Dekkoo",
            "provider_id": 444
        }
    },
    {
        "model": "movies.ott",
        "pk": 176,
        "fields": {
            "logo_path": "/aRPDQvVcpeY07sjI6lAALMCL0ti.jpg",
            "provider_name": "True Story",
            "provider_id": 567
        }
    },
    {
        "model": "movies.ott",
        "pk": 177,
        "fields": {
            "logo_path": "/vbXJBJVv3u3YWt6ml0l0ldDblXT.jpg",
            "provider_name": "DocAlliance Films",
            "provider_id": 569
        }
    },
    {
        "model": "movies.ott",
        "pk": 178,
        "fields": {
            "logo_path": "/u7dwMceEbjxd1N3TLEUBILSK2x6.jpg",
            "provider_name": "Hoichoi",
            "provider_id": 315
        }
    },
    {
        "model": "movies.ott",
        "pk": 179,
        "fields": {
            "logo_path": "/fwx5Ed64TkfWiRH1SOSkc4781Ts.jpg",
            "provider_name": "Eventive",
            "provider_id": 677
        }
    },
    {
        "model": "movies.ott",
        "pk": 180,
        "fields": {
            "logo_path": "/uauVx3dGWt0GICqdMCBYJObd3Mo.jpg",
            "provider_name": "Cultpix",
            "provider_id": 692
        }
    },
    {
        "model": "movies.ott",
        "pk": 181,
        "fields": {
            "logo_path": "/fbveJTcro9Xw2KuPIIoPPePHiwy.jpg",
            "provider_name": "FilmBox+",
            "provider_id": 701
        }
    },
    {
        "model": "movies.ott",
        "pk": 182,
        "fields": {
            "logo_path": "/ed0vz5bryWIhQB5sHiuGvHKnHHn.jpg",
            "provider_name": "Takflix",
            "provider_id": 1771
        }
    },
    {
        "model": "movies.ott",
        "pk": 183,
        "fields": {
            "logo_path": "/6KEQzITx2RrCAQt5Nw9WrL1OI8z.jpg",
            "provider_name": "Sun Nxt",
            "provider_id": 309
        }
    },
    {
        "model": "movies.ott",
        "pk": 184,
        "fields": {
            "logo_path": "/uFjAjvrKMII0H766QzyHDNkZdKX.jpg",
            "provider_name": "Classix",
            "provider_id": 445
        }
    },
    {
        "model": "movies.ott",
        "pk": 185,
        "fields": {
            "logo_path": "/mXeC4TrcgdU6ltE9bCBCEORwSQR.jpg",
            "provider_name": "Crunchyroll",
            "provider_id": 283
        }
    }
]